myjdapi/__init__.py
myjdapi/const.py
myjdapi/exception.py
myjdapi/myjdapi.py
myjdapi-1.1.10.dist-info/licenses/LICENSE
myjdapi-1.1.10.dist-info/METADATA
myjdapi-1.1.10.dist-info/WHEEL
myjdapi-1.1.10.dist-info/top_level.txt
myjdapi-1.1.10.dist-info/RECORD
