Metadata-Version: 2.4
Name: myjdapi
Version: 1.1.10
Summary: Library to use My.Jdownloader API in an easy way.
Home-page: https://github.com/mmarquezs/My.Jdownloader-API-Python-Library/
Author: Marc Marquez Santamaria
Author-email: mmsa1994@gmail.com
License: MIT
Keywords: myjdapi jdownloader my.jdownloader api development
Classifier: Development Status :: 3 - Alpha
Classifier: Intended Audience :: Developers
Classifier: Topic :: Software Development :: Libraries
Classifier: License :: OSI Approved :: MIT License
Classifier: Programming Language :: Python :: 3
Classifier: Programming Language :: Python :: 3.2
Classifier: Programming Language :: Python :: 3.3
Classifier: Programming Language :: Python :: 3.4
Classifier: Programming Language :: Python :: 3.5
License-File: LICENSE
Requires-Dist: requests
Requires-Dist: pycryptodome
Dynamic: author
Dynamic: author-email
Dynamic: classifier
Dynamic: description
Dynamic: home-page
Dynamic: keywords
Dynamic: license
Dynamic: license-file
Dynamic: requires-dist
Dynamic: summary
